colorobject/__init__.py
colorobject/base_objects.py
colorobject/colormaps.py
colorobject/colorobject.py
colorobject/data.py
colorobject/discretecolors.py
colorobject-0.8.1.dist-info/DESCRIPTION.rst
colorobject-0.8.1.dist-info/METADATA
colorobject-0.8.1.dist-info/metadata.json
colorobject-0.8.1.dist-info/RECORD
colorobject-0.8.1.dist-info/top_level.txt
colorobject-0.8.1.dist-info/WHEEL
