Metadata-Version: 2.0
Name: colorobject
Version: 0.8.1
Summary: Dynamic color objects compatible with Matplotlib
Home-page: UNKNOWN
Author: Gen Del Raye
Author-email: gdelraye@hawaii.edu
License: UNKNOWN
Keywords: matplotlib,color,hls,hsv,color name,colormap
Platform: UNKNOWN
Classifier: Intended Audience :: Science/Research
Classifier: License :: OSI Approved :: GNU General Public License v3 (GPLv3)
Classifier: Natural Language :: English
Classifier: Operating System :: OS Independent
Classifier: Programming Language :: Python
Classifier: Topic :: Scientific/Engineering
Classifier: Development Status :: 4 - Beta
